{
  "Fungal infection": {
    "symptoms": [
      "itching",
      "skin rash",
      "nodal skin eruptions",
      "dischromic  patches"
    ],
    "precautions": [
      "bath twice",
      "use detol or neem in bathing water",
      "keep infected area dry",
      "use clean cloths"
    ]
  },
  "Allergy": {
    "symptoms": [
      "continuous sneezing",
      "shivering",
      "chills",
      "watering from eyes"
    ],
    "precautions": [
      "apply calamine",
      "cover area with bandage",
      "use ice to compress itching"
    ]
  },
  "GERD": {
    "symptoms": [
      "stomach pain",
      "acidity",
      "ulcers on tongue",
      "vomiting",
      "cough",
      "chest pain"
    ],
    "precautions": [
      "avoid fatty spicy food",
      "avoid lying down after eating",
      "maintain healthy weight",
      "exercise"
    ]
  },
  "Chronic cholestasis": {
    "symptoms": [
      "itching",
      "vomiting",
      "yellowish skin",
      "nausea",
      "loss of appetite",
      "abdominal pain",
      "yellowing of eyes"
    ],
    "precautions": [
      "cold baths",
      "anti itch medicine",
      "consult doctor",
      "eat healthy"
    ]
  },
  "Drug Reaction": {
    "symptoms": [
      "itching",
      "skin rash",
      "stomach pain",
      "burning micturition",
      "spotting  urination"
    ],
    "precautions": [
      "stop irritation",
      "consult nearest hospital",
      "stop taking drug",
      "follow up"
    ]
  },
  "Peptic ulcer diseae": {
    "symptoms": [
      "vomiting",
      "loss of appetite",
      "abdominal pain",
      "passage of gases",
      "internal itching",
      "indigestion"
    ],
    "precautions": [
      "avoid fatty spicy food",
      "consume probiotic food",
      "eliminate milk",
      "limit alcohol"
    ]
  },
  "AIDS": {
    "symptoms": [
      "muscle wasting",
      "patches in throat",
      "high fever",
      "extra marital contacts"
    ],
    "precautions": [
      "avoid open cuts",
      "wear ppe if possible",
      "consult doctor",
      "follow up"
    ]
  },
  "Diabetes": {
    "symptoms": [
      "fatigue",
      "weight loss",
      "restlessness",
      "lethargy",
      "irregular sugar level",
      "blurred and distorted vision",
      "obesity",
      "excessive hunger",
      "increased appetite",
      "polyuria"
    ],
    "precautions": [
      "have balanced diet",
      "exercise",
      "consult doctor",
      "follow up"
    ]
  },
  "Gastroenteritis": {
    "symptoms": [
      "vomiting",
      "sunken eyes",
      "dehydration",
      "diarrhoea"
    ],
    "precautions": [
      "stop eating solid food for while",
      "try taking small sips of water",
      "rest",
      "ease back into eating"
    ]
  },
  "Bronchial Asthma": {
    "symptoms": [
      "fatigue",
      "cough",
      "high fever",
      "breathlessness",
      "family history",
      "mucoid sputum"
    ],
    "precautions": [
      "switch to loose cloothing",
      "take deep breaths",
      "get away from trigger",
      "seek help"
    ]
  },
  "Hypertension": {
    "symptoms": [
      "headache",
      "chest pain",
      "dizziness",
      "loss of balance",
      "lack of concentration"
    ],
    "precautions": [
      "meditation",
      "salt baths",
      "reduce stress",
      "get proper sleep"
    ]
  },
  "Migraine": {
    "symptoms": [
      "acidity",
      "indigestion",
      "headache",
      "blurred and distorted vision",
      "excessive hunger",
      "stiff neck",
      "depression",
      "irritability",
      "visual disturbances"
    ],
    "precautions": [
      "meditation",
      "reduce stress",
      "use poloroid glasses in sun",
      "consult doctor"
    ]
  },
  "Cervical spondylosis": {
    "symptoms": [
      "back pain",
      "weakness in limbs",
      "neck pain",
      "dizziness",
      "loss of balance"
    ],
    "precautions": [
      "use heating pad or cold pack",
      "exercise",
      "take otc pain reliver",
      "consult doctor"
    ]
  },
  "Paralysis (brain hemorrhage)": {
    "symptoms": [
      "vomiting",
      "headache",
      "weakness of one body side",
      "altered sensorium"
    ],
    "precautions": [
      "massage",
      "eat healthy",
      "exercise",
      "consult doctor"
    ]
  },
  "Jaundice": {
    "symptoms": [
      "itching",
      "vomiting",
      "fatigue",
      "weight loss",
      "high fever",
      "yellowish skin",
      "dark urine",
      "abdominal pain"
    ],
    "precautions": [
      "drink plenty of water",
      "consume milk thistle",
      "eat fruits and high fiberous food",
      "medication"
    ]
  },
  "Malaria": {
    "symptoms": [
      "chills",
      "vomiting",
      "high fever",
      "sweating",
      "headache",
      "nausea",
      "muscle pain",
      "diarrhoea"
    ],
    "precautions": [
      "Consult nearest hospital",
      "avoid oily food",
      "avoid non veg food",
      "keep mosquitos out"
    ]
  },
  "Chicken pox": {
    "symptoms": [
      "itching",
      "skin rash",
      "fatigue",
      "lethargy",
      "high fever",
      "headache",
      "loss of appetite",
      "mild fever",
      "swelled lymph nodes",
      "malaise",
      "red spots over body"
    ],
    "precautions": [
      "use neem in bathing",
      "consume neem leaves",
      "take vaccine",
      "avoid public places"
    ]
  },
  "Dengue": {
    "symptoms": [
      "skin rash",
      "chills",
      "joint pain",
      "vomiting",
      "fatigue",
      "high fever",
      "headache",
      "nausea",
      "loss of appetite",
      "pain behind the eyes",
      "back pain",
      "muscle pain",
      "red spots over body",
      "malaise"
    ],
    "precautions": [
      "drink papaya leaf juice",
      "avoid fatty spicy food",
      "keep mosquitos away",
      "keep hydrated"
    ]
  },
  "Typhoid": {
    "symptoms": [
      "chills",
      "vomiting",
      "fatigue",
      "high fever",
      "nausea",
      "constipation",
      "abdominal pain",
      "diarrhoea",
      "toxic look (typhos)",
      "belly pain",
      "headache"
    ],
    "precautions": [
      "eat high calorie vegitables",
      "antiboitic therapy",
      "consult doctor",
      "medication"
    ]
  },
  "hepatitis A": {
    "symptoms": [
      "joint pain",
      "vomiting",
      "yellowish skin",
      "dark urine",
      "nausea",
      "loss of appetite",
      "abdominal pain",
      "diarrhoea",
      "mild fever",
      "yellowing of eyes",
      "muscle pain"
    ],
    "precautions": [
      "Consult nearest hospital",
      "wash hands through",
      "avoid fatty spicy food",
      "medication"
    ]
  },
  "Hepatitis B": {
    "symptoms": [
      "itching",
      "fatigue",
      "lethargy",
      "yellowish skin",
      "dark urine",
      "loss of appetite",
      "abdominal pain",
      "yellow urine",
      "yellowing of eyes",
      "malaise",
      "receiving blood transfusion",
      "receiving unsterile injections"
    ],
    "precautions": [
      "consult nearest hospital",
      "vaccination",
      "eat healthy",
      "medication"
    ]
  },
  "Hepatitis C": {
    "symptoms": [
      "fatigue",
      "yellowish skin",
      "nausea",
      "loss of appetite",
      "family history",
      "yellowing of eyes"
    ],
    "precautions": [
      "Consult nearest hospital",
      "vaccination",
      "eat healthy",
      "medication"
    ]
  },
  "Hepatitis D": {
    "symptoms": [
      "joint pain",
      "vomiting",
      "fatigue",
      "yellowish skin",
      "dark urine",
      "nausea",
      "loss of appetite",
      "abdominal pain",
      "yellowing of eyes"
    ],
    "precautions": [
      "consult doctor",
      "medication",
      "eat healthy",
      "follow up"
    ]
  },
  "Hepatitis E": {
    "symptoms": [
      "joint pain",
      "vomiting",
      "fatigue",
      "high fever",
      "yellowish skin",
      "dark urine",
      "nausea",
      "loss of appetite",
      "abdominal pain",
      "yellowing of eyes",
      "coma",
      "stomach bleeding",
      "acute liver failure"
    ],
    "precautions": [
      "stop alcohol consumption",
      "rest",
      "consult doctor",
      "medication"
    ]
  },
  "Alcoholic hepatitis": {
    "symptoms": [
      "vomiting",
      "yellowish skin",
      "abdominal pain",
      "swelling of stomach",
      "distention of abdomen",
      "history of alcohol consumption",
      "fluid overload"
    ],
    "precautions": [
      "stop alcohol consumption",
      "consult doctor",
      "medication",
      "follow up"
    ]
  },
  "Tuberculosis": {
    "symptoms": [
      "chills",
      "vomiting",
      "fatigue",
      "weight loss",
      "cough",
      "high fever",
      "breathlessness",
      "sweating",
      "loss of appetite",
      "mild fever",
      "yellowing of eyes",
      "swelled lymph nodes",
      "malaise",
      "phlegm",
      "chest pain",
      "blood in sputum"
    ],
    "precautions": [
      "cover mouth",
      "consult doctor",
      "medication",
      "rest"
    ]
  },
  "Common Cold": {
    "symptoms": [
      "continuous sneezing",
      "chills",
      "fatigue",
      "cough",
      "high fever",
      "headache",
      "swelled lymph nodes",
      "malaise",
      "phlegm",
      "throat irritation",
      "redness of eyes",
      "sinus pressure",
      "runny nose",
      "congestion",
      "chest pain",
      "loss of smell",
      "muscle pain"
    ],
    "precautions": [
      "drink vitamin c rich drinks",
      "take vapour",
      "avoid cold food",
      "keep fever in check"
    ]
  },
  "Pneumonia": {
    "symptoms": [
      "chills",
      "fatigue",
      "cough",
      "high fever",
      "breathlessness",
      "sweating",
      "malaise",
      "chest pain",
      "fast heart rate",
      "rusty sputum",
      "phlegm"
    ],
    "precautions": [
      "consult doctor",
      "medication",
      "rest",
      "follow up"
    ]
  },
  "Dimorphic hemmorhoids(piles)": {
    "symptoms": [
      "constipation",
      "pain during bowel movements",
      "pain in anal region",
      "bloody stool",
      "irritation in anus"
    ],
    "precautions": [
      "avoid fatty spicy food",
      "consume witch hazel",
      "warm bath with epsom salt",
      "consume alovera juice"
    ]
  },
  "Heart attack": {
    "symptoms": [
      "vomiting",
      "breathlessness",
      "sweating",
      "chest pain"
    ],
    "precautions": [
      "call ambulance",
      "chew or swallow asprin",
      "keep calm"
    ]
  },
  "Varicose veins": {
    "symptoms": [
      "fatigue",
      "cramps",
      "bruising",
      "obesity",
      "swollen legs",
      "swollen blood vessels",
      "prominent veins on calf"
    ],
    "precautions": [
      "lie down flat and raise the leg high",
      "use oinments",
      "use vein compression",
      "dont stand still for long"
    ]
  },
  "Hypothyroidism": {
    "symptoms": [
      "fatigue",
      "weight gain",
      "cold hands and feets",
      "mood swings",
      "lethargy",
      "dizziness",
      "puffy face and eyes",
      "enlarged thyroid",
      "brittle nails",
      "swollen extremeties",
      "depression",
      "irritability",
      "abnormal menstruation"
    ],
    "precautions": [
      "reduce stress",
      "exercise",
      "eat healthy",
      "get proper sleep"
    ]
  },
  "Hyperthyroidism": {
    "symptoms": [
      "fatigue",
      "mood swings",
      "weight loss",
      "restlessness",
      "sweating",
      "diarrhoea",
      "fast heart rate",
      "excessive hunger",
      "muscle weakness",
      "irritability",
      "abnormal menstruation"
    ],
    "precautions": [
      "eat healthy",
      "massage",
      "use lemon balm",
      "take radioactive iodine treatment"
    ]
  },
  "Hypoglycemia": {
    "symptoms": [
      "vomiting",
      "fatigue",
      "anxiety",
      "sweating",
      "headache",
      "nausea",
      "blurred and distorted vision",
      "excessive hunger",
      "slurred speech",
      "irritability",
      "palpitations",
      "drying and tingling lips"
    ],
    "precautions": [
      "lie down on side",
      "check in pulse",
      "drink sugary drinks",
      "consult doctor"
    ]
  },
  "Osteoarthristis": {
    "symptoms": [
      "joint pain",
      "neck pain",
      "knee pain",
      "hip joint pain",
      "swelling joints",
      "painful walking"
    ],
    "precautions": [
      "acetaminophen",
      "consult nearest hospital",
      "follow up",
      "salt baths"
    ]
  },
  "Arthritis": {
    "symptoms": [
      "muscle weakness",
      "stiff neck",
      "swelling joints",
      "movement stiffness",
      "painful walking"
    ],
    "precautions": [
      "exercise",
      "use hot and cold therapy",
      "try acupuncture",
      "massage"
    ]
  },
  "(vertigo) Paroymsal  Positional Vertigo": {
    "symptoms": [
      "vomiting",
      "headache",
      "nausea",
      "spinning movements",
      "loss of balance",
      "unsteadiness"
    ],
    "precautions": [
      "lie down",
      "avoid sudden change in body",
      "avoid abrupt head movment",
      "relax"
    ]
  },
  "Acne": {
    "symptoms": [
      "skin rash",
      "pus filled pimples",
      "blackheads",
      "scurring"
    ],
    "precautions": [
      "bath twice",
      "avoid fatty spicy food",
      "drink plenty of water",
      "avoid too many products"
    ]
  },
  "Urinary tract infection": {
    "symptoms": [
      "burning micturition",
      "bladder discomfort",
      "foul smell of urine",
      "continuous feel of urine"
    ],
    "precautions": [
      "drink plenty of water",
      "increase vitamin c intake",
      "drink cranberry juice",
      "take probiotics"
    ]
  },
  "Psoriasis": {
    "symptoms": [
      "skin rash",
      "joint pain",
      "skin peeling",
      "silver like dusting",
      "small dents in nails",
      "inflammatory nails"
    ],
    "precautions": [
      "wash hands with warm soapy water",
      "stop bleeding using pressure",
      "consult doctor",
      "salt baths"
    ]
  },
  "Impetigo": {
    "symptoms": [
      "skin rash",
      "high fever",
      "blister",
      "red sore around nose",
      "yellow crust ooze"
    ],
    "precautions": [
      "soak affected area in warm water",
      "use antibiotics",
      "remove scabs with wet compressed cloth",
      "consult doctor"
    ]
  }
}